cybertensor/__init__.py
cybertensor/axon.py
cybertensor/chain_data.py
cybertensor/cli.py
cybertensor/config.py
cybertensor/ctlogging.py
cybertensor/cwtensor.py
cybertensor/dendrite.py
cybertensor/errors.py
cybertensor/keyfile.py
cybertensor/keypair.py
cybertensor/metagraph.py
cybertensor/stream.py
cybertensor/subnets.py
cybertensor/synapse.py
cybertensor/tensor.py
cybertensor/threadpool.py
cybertensor/types.py
cybertensor/wallet.py
cybertensor/commands/__init__.py
cybertensor/commands/delegates.py
cybertensor/commands/identity.py
cybertensor/commands/inspect.py
cybertensor/commands/list.py
cybertensor/commands/metagraph.py
cybertensor/commands/network.py
cybertensor/commands/overview.py
cybertensor/commands/register.py
cybertensor/commands/root.py
cybertensor/commands/stake.py
cybertensor/commands/transfer.py
cybertensor/commands/unstake.py
cybertensor/commands/utils.py
cybertensor/commands/wallets.py
cybertensor/messages/__init__.py
cybertensor/messages/delegation.py
cybertensor/messages/network.py
cybertensor/messages/prometheus.py
cybertensor/messages/registration.py
cybertensor/messages/root.py
cybertensor/messages/serving.py
cybertensor/messages/set_weights.py
cybertensor/messages/staking.py
cybertensor/messages/transfer.py
cybertensor/messages/unstaking.py
cybertensor/mock/__init__.py
cybertensor/mock/cwtensor_mock.py
cybertensor/mock/keyfile_mock.py
cybertensor/mock/wallet_mock.py
cybertensor/utils/__init__.py
cybertensor/utils/_register_cuda.py
cybertensor/utils/balance.py
cybertensor/utils/formatting.py
cybertensor/utils/networking.py
cybertensor/utils/registration.py
cybertensor/utils/wallet_utils.py
cybertensor/utils/weight_utils.py
cybertensor-0.2.4.data/scripts/ctcli
cybertensor-0.2.4.dist-info/LICENSE
cybertensor-0.2.4.dist-info/METADATA
cybertensor-0.2.4.dist-info/WHEEL
cybertensor-0.2.4.dist-info/top_level.txt
cybertensor-0.2.4.dist-info/RECORD
